{
    "task-info": {
        "domain": "rovers",
        "instance": 18,
        "ipc-year": "2006"
    },
    "planner-info": {
        "planner-tag": "exists-noprop",
        "planner-name": "SMTPlanner",
        "planner-params": {
            "encoder": "EncoderParallelSMT",
            "upper-bound": 1000,
            "search-strategy": "SMTSearch",
            "configuration": "exists-noprop",
            "run-validation": true,
            "compliation-list": [
                [
                    "up_quantifiers_remover",
                    "QUANTIFIERS_REMOVING"
                ],
                [
                    "fast-downward-reachability-grounder",
                    "GROUNDING"
                ]
            ]
        }
    },
    "task-result": {
        "timings": {
            "pddl-parse-time": 0.5048708915710449,
            "planning-time": 1109.617440700531
        },
        "summary": {
            "status": "SOLVED_SATISFICING",
            "log_messages": []
        },
        "plan": [
            "(calibrate rover1 camera0 objective4 waypoint9)",
            "(calibrate rover0 camera5 objective2 waypoint2)",
            "(sample_rock rover0 rover0store waypoint2)",
            "(navigate rover1 waypoint9 waypoint0)",
            "(navigate rover0 waypoint2 waypoint0)",
            "(navigate rover3 waypoint18 waypoint0)",
            "(navigate rover4 waypoint3 waypoint11)",
            "(navigate rover2 waypoint0 waypoint1)",
            "(calibrate rover2 camera1 objective6 waypoint1)",
            "(take_image rover1 waypoint0 objective4 camera0 high_res)",
            "(calibrate rover3 camera4 objective4 waypoint0)",
            "(navigate rover2 waypoint1 waypoint0)",
            "(take_image rover0 waypoint0 objective5 camera5 colour)",
            "(drop rover0 rover0store)",
            "(navigate rover1 waypoint0 waypoint16)",
            "(navigate rover4 waypoint11 waypoint18)",
            "(communicate_rock_data rover0 general waypoint2 waypoint0 waypoint17)",
            "(navigate rover5 waypoint0 waypoint12)",
            "(navigate rover3 waypoint0 waypoint1)",
            "(sample_soil rover2 rover2store waypoint0)",
            "(navigate rover4 waypoint18 waypoint11)",
            "(navigate rover3 waypoint1 waypoint7)",
            "(communicate_image_data rover0 general objective5 colour waypoint0 waypoint17)",
            "(take_image rover2 waypoint0 objective3 camera1 low_res)",
            "(take_image rover3 waypoint7 objective4 camera4 high_res)",
            "(navigate rover5 waypoint12 waypoint5)",
            "(calibrate rover2 camera1 objective6 waypoint0)",
            "(sample_rock rover3 rover3store waypoint7)",
            "(communicate_image_data rover2 general objective3 low_res waypoint0 waypoint17)",
            "(calibrate rover3 camera3 objective6 waypoint7)",
            "(navigate rover4 waypoint11 waypoint3)",
            "(navigate rover4 waypoint3 waypoint6)",
            "(navigate rover3 waypoint7 waypoint1)",
            "(navigate rover0 waypoint0 waypoint2)",
            "(communicate_soil_data rover2 general waypoint0 waypoint0 waypoint17)",
            "(take_image rover2 waypoint0 objective2 camera1 colour)",
            "(drop rover3 rover3store)",
            "(calibrate rover4 camera2 objective0 waypoint6)",
            "(sample_rock rover5 rover5store waypoint5)",
            "(sample_rock rover3 rover3store waypoint1)",
            "(navigate rover0 waypoint2 waypoint6)",
            "(communicate_image_data rover2 general objective2 colour waypoint0 waypoint17)",
            "(navigate rover4 waypoint6 waypoint14)",
            "(calibrate rover2 camera1 objective6 waypoint0)",
            "(navigate rover5 waypoint5 waypoint12)",
            "(navigate rover3 waypoint1 waypoint0)",
            "(navigate rover2 waypoint0 waypoint13)",
            "(sample_soil rover4 rover4store waypoint14)",
            "(take_image rover4 waypoint14 objective3 camera2 colour)",
            "(sample_rock rover0 rover0store waypoint6)",
            "(communicate_rock_data rover3 general waypoint7 waypoint0 waypoint17)",
            "(navigate rover5 waypoint12 waypoint4)",
            "(calibrate rover3 camera4 objective4 waypoint0)",
            "(take_image rover3 waypoint0 objective5 camera3 colour)",
            "(drop rover5 rover5store)",
            "(navigate rover1 waypoint16 waypoint0)",
            "(sample_rock rover5 rover5store waypoint4)",
            "(communicate_image_data rover1 general objective4 high_res waypoint0 waypoint17)",
            "(navigate rover4 waypoint14 waypoint6)",
            "(calibrate rover1 camera0 objective4 waypoint0)",
            "(navigate rover0 waypoint6 waypoint19)",
            "(navigate rover5 waypoint4 waypoint12)",
            "(navigate rover2 waypoint13 waypoint0)",
            "(navigate rover3 waypoint0 waypoint12)",
            "(calibrate rover4 camera2 objective0 waypoint6)",
            "(navigate rover5 waypoint12 waypoint0)",
            "(navigate rover3 waypoint12 waypoint19)",
            "(navigate rover1 waypoint0 waypoint16)",
            "(navigate rover4 waypoint6 waypoint3)",
            "(navigate rover2 waypoint0 waypoint1)",
            "(communicate_rock_data rover0 general waypoint6 waypoint19 waypoint17)",
            "(communicate_rock_data rover5 general waypoint5 waypoint0 waypoint17)",
            "(navigate rover4 waypoint3 waypoint9)",
            "(navigate rover0 waypoint19 waypoint6)",
            "(drop rover4 rover4store)",
            "(navigate rover4 waypoint9 waypoint19)",
            "(communicate_rock_data rover5 general waypoint4 waypoint0 waypoint17)",
            "(drop rover2 rover2store)",
            "(navigate rover3 waypoint19 waypoint12)",
            "(navigate rover0 waypoint6 waypoint2)",
            "(navigate rover2 waypoint1 waypoint2)",
            "(take_image rover3 waypoint12 objective3 camera4 high_res)",
            "(take_image rover2 waypoint2 objective5 camera1 colour)",
            "(drop rover0 rover0store)",
            "(navigate rover3 waypoint12 waypoint0)",
            "(take_image rover1 waypoint16 objective3 camera0 high_res)",
            "(sample_soil rover4 rover4store waypoint19)",
            "(calibrate rover5 camera6 objective6 waypoint0)",
            "(drop rover3 rover3store)",
            "(drop rover5 rover5store)",
            "(communicate_soil_data rover4 general waypoint14 waypoint19 waypoint17)",
            "(take_image rover4 waypoint19 objective3 camera2 high_res)"
        ]
    },
    "debug-info": {
        "domain-file": "/home/lr225/user-prop-run-1/domains/classical/rovers/domain.pddl",
        "problem-file": "/home/lr225/user-prop-run-1/domains/classical/rovers/p18.pddl"
    }
}